paramiko_tunnel
